TSB_AD/HP_list.py
TSB_AD/__init__.py
TSB_AD/main.py
TSB_AD/model_wrapper.py
TSB_AD/evaluation/__init__.py
TSB_AD/evaluation/basic_metrics.py
TSB_AD/evaluation/metrics.py
TSB_AD/evaluation/visualize.py
TSB_AD/evaluation/affiliation/__init__.py
TSB_AD/evaluation/affiliation/_affiliation_zone.py
TSB_AD/evaluation/affiliation/_integral_interval.py
TSB_AD/evaluation/affiliation/_single_ground_truth_event.py
TSB_AD/evaluation/affiliation/generics.py
TSB_AD/evaluation/affiliation/metrics.py
TSB_AD/models/AE.py
TSB_AD/models/AnomalyTransformer.py
TSB_AD/models/CBLOF.py
TSB_AD/models/CNN.py
TSB_AD/models/COF.py
TSB_AD/models/COPOD.py
TSB_AD/models/Chronos.py
TSB_AD/models/Donut.py
TSB_AD/models/EIF.py
TSB_AD/models/FFT.py
TSB_AD/models/FITS.py
TSB_AD/models/HBOS.py
TSB_AD/models/IForest.py
TSB_AD/models/KMeansAD.py
TSB_AD/models/KNN.py
TSB_AD/models/KShapeAD.py
TSB_AD/models/KShapeAD_tslearn.py
TSB_AD/models/LOF.py
TSB_AD/models/LSTMAD.py
TSB_AD/models/Lag_Llama.py
TSB_AD/models/Lag_Llama_path.py
TSB_AD/models/Left_STAMPi.py
TSB_AD/models/MCD.py
TSB_AD/models/MOMENT.py
TSB_AD/models/MatrixProfile.py
TSB_AD/models/NormA.py
TSB_AD/models/OCSVM.py
TSB_AD/models/OFA.py
TSB_AD/models/OmniAnomaly.py
TSB_AD/models/PCA.py
TSB_AD/models/POLY.py
TSB_AD/models/RobustPCA.py
TSB_AD/models/SAND.py
TSB_AD/models/SR.py
TSB_AD/models/Series2Graph.py
TSB_AD/models/TimesFM.py
TSB_AD/models/TimesNet.py
TSB_AD/models/TranAD.py
TSB_AD/models/USAD.py
TSB_AD/models/__init__.py
TSB_AD/models/base.py
TSB_AD/models/distance.py
TSB_AD/models/feature.py
TSB_AD/utils/__init__.py
TSB_AD/utils/dataset.py
TSB_AD/utils/slidingWindows.py
TSB_AD/utils/stat_models.py
TSB_AD/utils/torch_utility.py
TSB_AD/utils/utility.py
TSB_AD-1.5.dist-info/LICENSE
TSB_AD-1.5.dist-info/METADATA
TSB_AD-1.5.dist-info/WHEEL
TSB_AD-1.5.dist-info/top_level.txt
TSB_AD-1.5.dist-info/RECORD
