Metadata-Version: 2.1
Name: TSB_AD
Version: 1.5
Summary: Time-Series Anomaly Detection Benchmark
Home-page: https://github.com/TheDatumOrg/TSB-AD
Author: The Datum Lab
License: Apache-2.0 license
Classifier: Development Status :: 3 - Alpha
Classifier: Intended Audience :: Developers
Classifier: Topic :: Software Development :: Build Tools
Classifier: License :: OSI Approved :: Apache Software License
Classifier: Programming Language :: Python :: 3.9
Classifier: Programming Language :: Python :: 3.10
Classifier: Programming Language :: Python :: 3.11
Requires-Python: >=3.8
License-File: LICENSE
Requires-Dist: tqdm
Requires-Dist: torchinfo
Requires-Dist: h5py
Requires-Dist: einops
Requires-Dist: numpy <2.0,>=1.24.3
Requires-Dist: matplotlib >=3.7.5
Requires-Dist: pandas >=2.0.3
Requires-Dist: arch >=5.3.1
Requires-Dist: hurst >=0.0.5
Requires-Dist: tslearn >=0.6.3
Requires-Dist: cython >=3.0.10
Requires-Dist: scikit-learn >=1.3.2
Requires-Dist: stumpy >=1.12.0
Requires-Dist: networkx >=3.1
Requires-Dist: transformers >=4.38.0
Requires-Dist: torch >=1.8.0
